README.md
setup.py
src/tkinter_embed/__init__.py
src/tkinter_embed/data.zip
src/tkinter_embed.egg-info/PKG-INFO
src/tkinter_embed.egg-info/SOURCES.txt
src/tkinter_embed.egg-info/dependency_links.txt
src/tkinter_embed.egg-info/top_level.txt