Metadata-Version: 2.1
Name: tkinter-embed
Version: 1.0.5
Summary: Tkinter for Windows Embedded Python
Author: Tanix
Author-email: tanixlu@foxmail.com
Classifier: Programming Language :: Python :: 3.8
Classifier: Programming Language :: Python :: 3.9
Classifier: Programming Language :: Python :: 3.10
Classifier: Programming Language :: Python :: 3.11
Classifier: Programming Language :: Python :: 3.12
Classifier: Programming Language :: Python :: 3.13
Classifier: Operating System :: Microsoft :: Windows
Classifier: Topic :: Software Development
Requires-Python: >=3.8
